anki/_backend.py
anki/_legacy.py
anki/_rsbridge.pyi
anki/browser.py
anki/cards.py
anki/collection.py
anki/config.py
anki/consts.py
anki/db.py
anki/dbproxy.py
anki/decks.py
anki/errors.py
anki/exporting.py
anki/find.py
anki/hooks.py
anki/httpclient.py
anki/lang.py
anki/latex.py
anki/media.py
anki/models.py
anki/notes.py
anki/py.typed
anki/rsbackend.py
anki/sound.py
anki/stats.py
anki/statsbg.py
anki/stdmodels.py
anki/storage.py
anki/sync.py
anki/syncserver.py
anki/tags.py
anki/template.py
anki/types.py
anki/utils.py
anki/_vendor/stringcase.py
anki/foreign_data/__init__.py
anki/foreign_data/mnemosyne.py
anki/importing/__init__.py
anki/importing/anki2.py
anki/importing/apkg.py
anki/importing/base.py
anki/importing/csvfile.py
anki/importing/mnemo.py
anki/importing/noteimp.py
anki/scheduler/__init__.py
anki/scheduler/base.py
anki/scheduler/dummy.py
anki/scheduler/legacy.py
anki/scheduler/v3.py
anki/_backend_generated.py
anki/_fluent.py
anki/_rsbridge.so
anki/ankidroid_pb2.py
anki/ankidroid_pb2.pyi
anki/ankihub_pb2.py
anki/ankihub_pb2.pyi
anki/ankiweb_pb2.py
anki/ankiweb_pb2.pyi
anki/backend_pb2.py
anki/backend_pb2.pyi
anki/buildinfo.py
anki/card_rendering_pb2.py
anki/card_rendering_pb2.pyi
anki/cards_pb2.py
anki/cards_pb2.pyi
anki/collection_pb2.py
anki/collection_pb2.pyi
anki/config_pb2.py
anki/config_pb2.pyi
anki/deck_config_pb2.py
anki/deck_config_pb2.pyi
anki/decks_pb2.py
anki/decks_pb2.pyi
anki/frontend_pb2.py
anki/frontend_pb2.pyi
anki/generic_pb2.py
anki/generic_pb2.pyi
anki/hooks_gen.py
anki/i18n_pb2.py
anki/i18n_pb2.pyi
anki/image_occlusion_pb2.py
anki/image_occlusion_pb2.pyi
anki/import_export_pb2.py
anki/import_export_pb2.pyi
anki/links_pb2.py
anki/links_pb2.pyi
anki/media_pb2.py
anki/media_pb2.pyi
anki/notes_pb2.py
anki/notes_pb2.pyi
anki/notetypes_pb2.py
anki/notetypes_pb2.pyi
anki/scheduler_pb2.py
anki/scheduler_pb2.pyi
anki/search_pb2.py
anki/search_pb2.pyi
anki/stats_pb2.py
anki/stats_pb2.pyi
anki/sync_pb2.py
anki/sync_pb2.pyi
anki/tags_pb2.py
anki-25.9.1.dist-info/METADATA
anki-25.9.1.dist-info/WHEEL
anki-25.9.1.dist-info/RECORD
