Metadata-Version: 2.4
Name: anki
Version: 25.9.1
License-Expression: AGPL-3.0-or-later
Requires-Python: >=3.9
Requires-Dist: decorator
Requires-Dist: distro; sys_platform != 'darwin' and sys_platform != 'win32'
Requires-Dist: markdown
Requires-Dist: orjson
Requires-Dist: protobuf<8.0,>=6.0
Requires-Dist: requests[socks]
Requires-Dist: typing-extensions
